bwk/__init__.py
bwk/bwk.py
bwk/characters.py
bwk/screen.py
bwk-1.1.0.dist-info/METADATA
bwk-1.1.0.dist-info/WHEEL
bwk-1.1.0.dist-info/RECORD
